__init__.py
add_cats.py
add_cats_ewissel-0.0.1.dist-info/licenses/LICENSE
add_cats_ewissel-0.0.1.dist-info/METADATA
add_cats_ewissel-0.0.1.dist-info/WHEEL
add_cats_ewissel-0.0.1.dist-info/top_level.txt
add_cats_ewissel-0.0.1.dist-info/RECORD
