Metadata-Version: 2.4
Name: add_cats_ewissel
Version: 0.0.1
Summary: Adding cats to python messages / scripting
Author: E Wisel
License-Expression: MIT
Project-URL: Homepage, https://github.com/ewissel/add_cats
Project-URL: Issues, https://github.com/ewissel/add_cats/issues
Classifier: Programming Language :: Python :: 3
Classifier: Operating System :: OS Independent
Requires-Python: >=3.0
License-File: LICENSE
Dynamic: license-file
